[{"t":"1981-09-01T12:00:00Z","lat":22.5,"lon":160.5,"wind":null,"pressure":null,"status":"DS","category":null,"agency":null},{"t":"1981-09-01T15:00:00Z","lat":22.5,"lon":160.1,"wind":null,"pressure":null,"status":"DS","category":null,"agency":null},{"t":"1981-09-01T18:00:00Z","lat":22.4,"lon":159.6,"wind":null,"pressure":1010.0,"status":"MX","category":null,"agency":"tokyo"},{"t":"1981-09-01T21:00:00Z","lat":22.3,"lon":159.0,"wind":null,"pressure":null,"status":"MX","category":null,"agency":null},{"t":"1981-09-02T00:00:00Z","lat":22.2,"lon":158.4,"wind":null,"pressure":1010.0,"status":"MX","category":null,"agency":"tokyo"},{"t":"1981-09-02T03:00:00Z","lat":22.1,"lon":157.8,"wind":null,"pressure":null,"status":"MX","category":null,"agency":null},{"t":"1981-09-02T06:00:00Z","lat":22.0,"lon":157.2,"wind":null,"pressure":1008.0,"status":"MX","category":null,"agency":"tokyo"},{"t":"1981-09-02T09:00:00Z","lat":21.9,"lon":156.7,"wind":null,"pressure":null,"status":"MX","category":null,"agency":null},{"t":"1981-09-02T12:00:00Z","lat":21.9,"lon":156.2,"wind":null,"pressure":1006.0,"status":"TS","category":null,"agency":"tokyo"},{"t":"1981-09-02T15:00:00Z","lat":21.9,"lon":155.7,"wind":null,"pressure":null,"status":"TS","category":null,"agency":null},{"t":"1981-09-02T18:00:00Z","lat":22.0,"lon":155.2,"wind":null,"pressure":1004.0,"status":"TS","category":null,"agency":"tokyo"},{"t":"1981-09-02T21:00:00Z","lat":22.1,"lon":154.6,"wind":null,"pressure":null,"status":"TS","category":null,"agency":null},{"t":"1981-09-03T00:00:00Z","lat":22.2,"lon":154.1,"wind":null,"pressure":1000.0,"status":"TS","category":null,"agency":"tokyo"},{"t":"1981-09-03T03:00:00Z","lat":22.3,"lon":153.6,"wind":null,"pressure":null,"status":"TS","category":null,"agency":null},{"t":"1981-09-03T06:00:00Z","lat":22.4,"lon":153.2,"wind":45.0,"pressure":994.0,"status":"TS","category":0,"agency":"tokyo"},{"t":"1981-09-03T09:00:00Z","lat":22.6,"lon":152.7,"wind":48.0,"pressure":null,"status":"TS","category":0,"agency":null},{"t":"1981-09-03T12:00:00Z","lat":22.7,"lon":152.2,"wind":50.0,"pressure":992.0,"status":"TS","category":0,"agency":"tokyo"},{"t":"1981-09-03T15:00:00Z","lat":22.8,"lon":151.7,"wind":50.0,"pressure":null,"status":"TS","category":0,"agency":null},{"t":"1981-09-03T18:00:00Z","lat":22.9,"lon":151.3,"wind":50.0,"pressure":990.0,"status":"TS","category":0,"agency":"tokyo"},{"t":"1981-09-03T21:00:00Z","lat":23.0,"lon":150.8,"wind":53.0,"pressure":null,"status":"TS","category":0,"agency":null},{"t":"1981-09-04T00:00:00Z","lat":23.2,"lon":150.4,"wind":55.0,"pressure":985.0,"status":"TS","category":0,"agency":"tokyo"},{"t":"1981-09-04T03:00:00Z","lat":23.6,"lon":149.8,"wind":58.0,"pressure":null,"status":"TS","category":0,"agency":null},{"t":"1981-09-04T06:00:00Z","lat":23.9,"lon":149.3,"wind":60.0,"pressure":980.0,"status":"TS","category":0,"agency":"tokyo"},{"t":"1981-09-04T09:00:00Z","lat":24.3,"lon":148.8,"wind":63.0,"pressure":null,"status":"TS","category":0,"agency":null},{"t":"1981-09-04T12:00:00Z","lat":24.7,"lon":148.3,"wind":65.0,"pressure":975.0,"status":"TS","category":1,"agency":"tokyo"},{"t":"1981-09-04T15:00:00Z","lat":25.1,"lon":147.8,"wind":70.0,"pressure":null,"status":"TS","category":1,"agency":null},{"t":"1981-09-04T18:00:00Z","lat":25.4,"lon":147.4,"wind":75.0,"pressure":970.0,"status":"TS","category":1,"agency":"tokyo"},{"t":"1981-09-04T21:00:00Z","lat":25.7,"lon":147.0,"wind":80.0,"pressure":null,"status":"TS","category":1,"agency":null},{"t":"1981-09-05T00:00:00Z","lat":26.1,"lon":146.6,"wind":85.0,"pressure":960.0,"status":"TS","category":2,"agency":"tokyo"},{"t":"1981-09-05T03:00:00Z","lat":26.6,"lon":146.3,"wind":85.0,"pressure":null,"status":"TS","category":2,"agency":null},{"t":"1981-09-05T06:00:00Z","lat":27.1,"lon":146.0,"wind":85.0,"pressure":960.0,"status":"TS","category":2,"agency":"tokyo"},{"t":"1981-09-05T09:00:00Z","lat":27.7,"lon":145.8,"wind":85.0,"pressure":null,"status":"TS","category":2,"agency":null},{"t":"1981-09-05T12:00:00Z","lat":28.3,"lon":145.6,"wind":85.0,"pressure":960.0,"status":"TS","category":2,"agency":"tokyo"},{"t":"1981-09-05T15:00:00Z","lat":28.8,"lon":145.5,"wind":85.0,"pressure":null,"status":"TS","category":2,"agency":null},{"t":"1981-09-05T18:00:00Z","lat":29.4,"lon":145.5,"wind":85.0,"pressure":960.0,"status":"TS","category":2,"agency":"tokyo"},{"t":"1981-09-05T21:00:00Z","lat":30.1,"lon":145.5,"wind":83.0,"pressure":null,"status":"TS","category":2,"agency":null},{"t":"1981-09-06T00:00:00Z","lat":30.9,"lon":145.6,"wind":80.0,"pressure":960.0,"status":"TS","category":1,"agency":"tokyo"},{"t":"1981-09-06T03:00:00Z","lat":31.8,"lon":145.8,"wind":78.0,"pressure":null,"status":"TS","category":1,"agency":null},{"t":"1981-09-06T06:00:00Z","lat":32.7,"lon":146.2,"wind":75.0,"pressure":965.0,"status":"TS","category":1,"agency":"tokyo"},{"t":"1981-09-06T09:00:00Z","lat":33.6,"lon":146.7,"wind":73.0,"pressure":null,"status":"TS","category":1,"agency":null},{"t":"1981-09-06T12:00:00Z","lat":34.6,"lon":147.4,"wind":70.0,"pressure":970.0,"status":"TS","category":1,"agency":"tokyo"},{"t":"1981-09-06T15:00:00Z","lat":35.6,"lon":148.3,"wind":65.0,"pressure":null,"status":"TS","category":1,"agency":null},{"t":"1981-09-06T18:00:00Z","lat":36.6,"lon":149.5,"wind":60.0,"pressure":970.0,"status":"TS","category":0,"agency":"tokyo"},{"t":"1981-09-06T21:00:00Z","lat":37.7,"lon":151.0,"wind":55.0,"pressure":null,"status":"TS","category":0,"agency":null},{"t":"1981-09-07T00:00:00Z","lat":38.7,"lon":152.8,"wind":50.0,"pressure":980.0,"status":"TS","category":0,"agency":"tokyo"},{"t":"1981-09-07T03:00:00Z","lat":39.6,"lon":154.8,"wind":45.0,"pressure":null,"status":"TS","category":0,"agency":null},{"t":"1981-09-07T06:00:00Z","lat":40.4,"lon":156.9,"wind":40.0,"pressure":990.0,"status":"MX","category":0,"agency":"tokyo"},{"t":"1981-09-07T09:00:00Z","lat":41.2,"lon":158.9,"wind":null,"pressure":null,"status":"ET","category":null,"agency":null},{"t":"1981-09-07T12:00:00Z","lat":42.1,"lon":161.3,"wind":null,"pressure":990.0,"status":"ET","category":null,"agency":"tokyo"},{"t":"1981-09-07T15:00:00Z","lat":42.9,"lon":164.1,"wind":null,"pressure":null,"status":"ET","category":null,"agency":null},{"t":"1981-09-07T18:00:00Z","lat":43.7,"lon":167.0,"wind":null,"pressure":992.0,"status":"ET","category":null,"agency":"tokyo"},{"t":"1981-09-07T21:00:00Z","lat":44.4,"lon":169.6,"wind":null,"pressure":null,"status":"ET","category":null,"agency":null},{"t":"1981-09-08T00:00:00Z","lat":45.0,"lon":172.0,"wind":null,"pressure":992.0,"status":"ET","category":null,"agency":"tokyo"},{"t":"1981-09-08T03:00:00Z","lat":45.5,"lon":174.5,"wind":null,"pressure":null,"status":"ET","category":null,"agency":null},{"t":"1981-09-08T06:00:00Z","lat":46.0,"lon":177.0,"wind":null,"pressure":994.0,"status":"ET","category":null,"agency":"tokyo"},{"t":"1981-09-08T09:00:00Z","lat":46.5,"lon":179.5,"wind":null,"pressure":null,"status":"ET","category":null,"agency":null},{"t":"1981-09-08T12:00:00Z","lat":47.0,"lon":182.0,"wind":null,"pressure":null,"status":"ET","category":null,"agency":null}]