[{"t":"1999-07-09T12:00:00Z","lat":26.0,"lon":129.0,"wind":null,"pressure":null,"status":"TS","category":null,"agency":null},{"t":"1999-07-09T15:00:00Z","lat":26.2,"lon":128.9,"wind":null,"pressure":null,"status":"TS","category":null,"agency":null},{"t":"1999-07-09T18:00:00Z","lat":26.6,"lon":128.8,"wind":null,"pressure":null,"status":"TS","category":null,"agency":null},{"t":"1999-07-09T21:00:00Z","lat":27.1,"lon":128.9,"wind":null,"pressure":null,"status":"TS","category":null,"agency":null},{"t":"1999-07-10T00:00:00Z","lat":27.5,"lon":129.0,"wind":null,"pressure":null,"status":"TS","category":null,"agency":null},{"t":"1999-07-10T03:00:00Z","lat":27.6,"lon":129.0,"wind":null,"pressure":null,"status":"TS","category":null,"agency":null},{"t":"1999-07-10T06:00:00Z","lat":27.5,"lon":129.0,"wind":null,"pressure":null,"status":"TS","category":null,"agency":null},{"t":"1999-07-10T09:00:00Z","lat":27.4,"lon":129.3,"wind":null,"pressure":null,"status":"TS","category":null,"agency":null},{"t":"1999-07-10T12:00:00Z","lat":27.2,"lon":129.8,"wind":null,"pressure":null,"status":"TS","category":null,"agency":null},{"t":"1999-07-10T15:00:00Z","lat":27.1,"lon":130.2,"wind":null,"pressure":null,"status":"TS","category":null,"agency":null},{"t":"1999-07-10T18:00:00Z","lat":27.0,"lon":130.6,"wind":null,"pressure":null,"status":"TS","category":null,"agency":null},{"t":"1999-07-10T21:00:00Z","lat":26.9,"lon":131.1,"wind":null,"pressure":null,"status":"TS","category":null,"agency":null},{"t":"1999-07-11T00:00:00Z","lat":26.8,"lon":131.5,"wind":null,"pressure":null,"status":"TS","category":null,"agency":null},{"t":"1999-07-11T03:00:00Z","lat":26.9,"lon":131.8,"wind":null,"pressure":null,"status":"TS","category":null,"agency":null},{"t":"1999-07-11T06:00:00Z","lat":27.0,"lon":132.0,"wind":null,"pressure":null,"status":"TS","category":null,"agency":null},{"t":"1999-07-11T09:00:00Z","lat":27.1,"lon":132.3,"wind":null,"pressure":null,"status":"TS","category":null,"agency":null},{"t":"1999-07-11T12:00:00Z","lat":27.2,"lon":132.5,"wind":null,"pressure":null,"status":"TS","category":null,"agency":null},{"t":"1999-07-11T15:00:00Z","lat":27.4,"lon":132.7,"wind":null,"pressure":null,"status":"TS","category":null,"agency":null},{"t":"1999-07-11T18:00:00Z","lat":27.6,"lon":132.9,"wind":null,"pressure":null,"status":"TS","category":null,"agency":null},{"t":"1999-07-11T21:00:00Z","lat":27.8,"lon":133.0,"wind":null,"pressure":null,"status":"TS","category":null,"agency":null},{"t":"1999-07-12T00:00:00Z","lat":28.0,"lon":133.0,"wind":null,"pressure":null,"status":"TS","category":null,"agency":null},{"t":"1999-07-12T03:00:00Z","lat":28.2,"lon":133.1,"wind":null,"pressure":null,"status":"TS","category":null,"agency":null},{"t":"1999-07-12T06:00:00Z","lat":28.3,"lon":133.1,"wind":null,"pressure":null,"status":"TS","category":null,"agency":null},{"t":"1999-07-12T09:00:00Z","lat":28.4,"lon":133.1,"wind":null,"pressure":null,"status":"TS","category":null,"agency":null},{"t":"1999-07-12T12:00:00Z","lat":28.5,"lon":133.2,"wind":null,"pressure":null,"status":"TS","category":null,"agency":null},{"t":"1999-07-12T15:00:00Z","lat":28.7,"lon":133.3,"wind":null,"pressure":null,"status":"TS","category":null,"agency":null},{"t":"1999-07-12T18:00:00Z","lat":28.8,"lon":133.4,"wind":null,"pressure":null,"status":"TS","category":null,"agency":null},{"t":"1999-07-12T21:00:00Z","lat":28.9,"lon":133.4,"wind":null,"pressure":null,"status":"TS","category":null,"agency":null},{"t":"1999-07-13T00:00:00Z","lat":29.0,"lon":133.5,"wind":null,"pressure":null,"status":"TS","category":null,"agency":null},{"t":"1999-07-13T03:00:00Z","lat":29.1,"lon":133.8,"wind":null,"pressure":null,"status":"TS","category":null,"agency":null},{"t":"1999-07-13T06:00:00Z","lat":29.2,"lon":134.1,"wind":null,"pressure":null,"status":"TS","category":null,"agency":null},{"t":"1999-07-13T09:00:00Z","lat":29.4,"lon":134.3,"wind":null,"pressure":null,"status":"TS","category":null,"agency":null},{"t":"1999-07-13T12:00:00Z","lat":29.7,"lon":134.5,"wind":null,"pressure":null,"status":"TS","category":null,"agency":null},{"t":"1999-07-13T15:00:00Z","lat":30.0,"lon":134.7,"wind":null,"pressure":null,"status":"TS","category":null,"agency":null},{"t":"1999-07-13T18:00:00Z","lat":30.3,"lon":134.9,"wind":null,"pressure":null,"status":"TS","category":null,"agency":null},{"t":"1999-07-13T21:00:00Z","lat":30.5,"lon":134.9,"wind":null,"pressure":null,"status":"TS","category":null,"agency":null},{"t":"1999-07-14T00:00:00Z","lat":30.8,"lon":135.2,"wind":null,"pressure":null,"status":"TS","category":null,"agency":null},{"t":"1999-07-14T03:00:00Z","lat":31.3,"lon":136.0,"wind":null,"pressure":null,"status":"TS","category":null,"agency":null},{"t":"1999-07-14T06:00:00Z","lat":32.0,"lon":137.0,"wind":null,"pressure":null,"status":"TS","category":null,"agency":null},{"t":"1999-07-14T09:00:00Z","lat":32.9,"lon":138.0,"wind":null,"pressure":null,"status":"TS","category":null,"agency":null},{"t":"1999-07-14T12:00:00Z","lat":34.0,"lon":139.0,"wind":null,"pressure":null,"status":"TS","category":null,"agency":null}]