[{"t":"2006-12-01T00:00:00Z","lat":-10.4,"lon":164.0,"wind":25.0,"pressure":1004.0,"status":"TS","category":-1,"agency":null},{"t":"2006-12-01T03:00:00Z","lat":-10.7,"lon":164.3,"wind":28.0,"pressure":1002.0,"status":"TS","category":-1,"agency":null},{"t":"2006-12-01T06:00:00Z","lat":-11.0,"lon":164.6,"wind":30.0,"pressure":1000.0,"status":"TS","category":-1,"agency":null},{"t":"2006-12-01T09:00:00Z","lat":-11.3,"lon":164.8,"wind":33.0,"pressure":999.0,"status":"TS","category":-1,"agency":null},{"t":"2006-12-01T12:00:00Z","lat":-11.7,"lon":164.9,"wind":35.0,"pressure":997.0,"status":"TS","category":0,"agency":null},{"t":"2006-12-01T15:00:00Z","lat":-12.0,"lon":165.0,"wind":35.0,"pressure":997.0,"status":"TS","category":0,"agency":null},{"t":"2006-12-01T18:00:00Z","lat":-12.3,"lon":165.0,"wind":35.0,"pressure":997.0,"status":"TS","category":0,"agency":null},{"t":"2006-12-01T21:00:00Z","lat":-12.4,"lon":165.0,"wind":30.0,"pressure":1000.0,"status":"TS","category":-1,"agency":null},{"t":"2006-12-02T00:00:00Z","lat":-12.5,"lon":165.0,"wind":25.0,"pressure":1002.0,"status":"TS","category":-1,"agency":null},{"t":"2006-12-02T03:00:00Z","lat":-12.5,"lon":165.0,"wind":25.0,"pressure":1002.0,"status":"TS","category":-1,"agency":null},{"t":"2006-12-02T06:00:00Z","lat":-12.6,"lon":165.0,"wind":25.0,"pressure":1002.0,"status":"TS","category":-1,"agency":null},{"t":"2006-12-02T09:00:00Z","lat":-12.9,"lon":164.9,"wind":25.0,"pressure":1002.0,"status":"TS","category":-1,"agency":null},{"t":"2006-12-02T12:00:00Z","lat":-13.2,"lon":164.7,"wind":25.0,"pressure":1002.0,"status":"TS","category":-1,"agency":null},{"t":"2006-12-02T15:00:00Z","lat":-13.4,"lon":164.3,"wind":25.0,"pressure":1002.0,"status":"TS","category":-1,"agency":null},{"t":"2006-12-02T18:00:00Z","lat":-13.6,"lon":163.9,"wind":25.0,"pressure":1002.0,"status":"TS","category":-1,"agency":null},{"t":"2006-12-02T21:00:00Z","lat":-13.8,"lon":163.5,"wind":25.0,"pressure":1002.0,"status":"TS","category":-1,"agency":null},{"t":"2006-12-03T00:00:00Z","lat":-14.0,"lon":163.1,"wind":25.0,"pressure":1002.0,"status":"TS","category":-1,"agency":null}]