[{"t":"2015-12-29T12:00:00Z","lat":-9.4,"lon":189.5,"wind":30.0,"pressure":1000.0,"status":"TS","category":-1,"agency":"nadi"},{"t":"2015-12-29T15:00:00Z","lat":-9.5,"lon":190.0,"wind":35.0,"pressure":997.0,"status":"TS","category":0,"agency":null},{"t":"2015-12-29T18:00:00Z","lat":-9.5,"lon":190.6,"wind":40.0,"pressure":993.0,"status":"TS","category":0,"agency":"nadi"},{"t":"2015-12-29T19:00:00Z","lat":-9.6,"lon":190.8,"wind":42.0,"pressure":992.0,"status":"TS","category":0,"agency":"nadi"},{"t":"2015-12-29T21:00:00Z","lat":-9.7,"lon":191.2,"wind":45.0,"pressure":989.0,"status":"TS","category":0,"agency":null},{"t":"2015-12-30T00:00:00Z","lat":-10.2,"lon":192.2,"wind":45.0,"pressure":989.0,"status":"TS","category":0,"agency":"nadi"},{"t":"2015-12-30T03:00:00Z","lat":-11.0,"lon":193.2,"wind":45.0,"pressure":989.0,"status":"TS","category":0,"agency":"nadi"},{"t":"2015-12-30T06:00:00Z","lat":-11.7,"lon":193.2,"wind":45.0,"pressure":989.0,"status":"TS","category":0,"agency":"nadi"},{"t":"2015-12-30T07:00:00Z","lat":-12.2,"lon":193.2,"wind":45.0,"pressure":989.0,"status":"TS","category":0,"agency":"nadi"},{"t":"2015-12-30T09:00:00Z","lat":-12.9,"lon":193.4,"wind":45.0,"pressure":989.0,"status":"TS","category":0,"agency":null},{"t":"2015-12-30T12:00:00Z","lat":-13.7,"lon":193.5,"wind":50.0,"pressure":985.0,"status":"TS","category":0,"agency":"nadi"},{"t":"2015-12-30T15:00:00Z","lat":-14.3,"lon":193.3,"wind":50.0,"pressure":985.0,"status":"TS","category":0,"agency":"nadi"},{"t":"2015-12-30T18:00:00Z","lat":-14.9,"lon":192.9,"wind":50.0,"pressure":985.0,"status":"TS","category":0,"agency":"nadi"},{"t":"2015-12-30T21:00:00Z","lat":-15.1,"lon":192.4,"wind":53.0,"pressure":984.0,"status":"TS","category":0,"agency":"nadi"},{"t":"2015-12-31T00:00:00Z","lat":-15.3,"lon":192.0,"wind":55.0,"pressure":982.0,"status":"TS","category":0,"agency":"nadi"},{"t":"2015-12-31T03:00:00Z","lat":-15.4,"lon":191.4,"wind":58.0,"pressure":980.0,"status":"TS","category":0,"agency":"nadi"},{"t":"2015-12-31T06:00:00Z","lat":-15.5,"lon":191.0,"wind":60.0,"pressure":978.0,"status":"TS","category":0,"agency":"nadi"},{"t":"2015-12-31T09:00:00Z","lat":-15.6,"lon":190.7,"wind":63.0,"pressure":976.0,"status":"TS","category":0,"agency":"nadi"},{"t":"2015-12-31T12:00:00Z","lat":-15.8,"lon":190.5,"wind":65.0,"pressure":974.0,"status":"TS","category":1,"agency":"nadi"},{"t":"2015-12-31T15:00:00Z","lat":-15.9,"lon":190.4,"wind":78.0,"pressure":965.0,"status":"TS","category":1,"agency":"nadi"},{"t":"2015-12-31T18:00:00Z","lat":-16.2,"lon":190.3,"wind":90.0,"pressure":956.0,"status":"TS","category":2,"agency":"nadi"},{"t":"2015-12-31T21:00:00Z","lat":-16.5,"lon":190.0,"wind":88.0,"pressure":958.0,"status":"TS","category":2,"agency":null},{"t":"2015-12-31T22:00:00Z","lat":-16.6,"lon":189.9,"wind":87.0,"pressure":958.0,"status":"TS","category":2,"agency":"nadi"},{"t":"2016-01-01T00:00:00Z","lat":-16.8,"lon":189.7,"wind":85.0,"pressure":959.0,"status":"TS","category":2,"agency":"nadi"},{"t":"2016-01-01T03:00:00Z","lat":-17.1,"lon":189.3,"wind":80.0,"pressure":963.0,"status":"TS","category":1,"agency":"nadi"},{"t":"2016-01-01T06:00:00Z","lat":-17.5,"lon":188.7,"wind":75.0,"pressure":967.0,"status":"TS","category":1,"agency":"nadi"},{"t":"2016-01-01T09:00:00Z","lat":-17.8,"lon":187.9,"wind":75.0,"pressure":967.0,"status":"TS","category":1,"agency":"nadi"},{"t":"2016-01-01T12:00:00Z","lat":-18.0,"lon":187.0,"wind":75.0,"pressure":967.0,"status":"TS","category":1,"agency":"nadi"},{"t":"2016-01-01T15:00:00Z","lat":-18.2,"lon":186.3,"wind":75.0,"pressure":967.0,"status":"TS","category":1,"agency":"nadi"},{"t":"2016-01-01T18:00:00Z","lat":-18.3,"lon":185.8,"wind":75.0,"pressure":967.0,"status":"TS","category":1,"agency":"nadi"},{"t":"2016-01-01T21:00:00Z","lat":-18.3,"lon":185.3,"wind":78.0,"pressure":965.0,"status":"TS","category":1,"agency":"nadi"},{"t":"2016-01-02T00:00:00Z","lat":-18.3,"lon":184.8,"wind":80.0,"pressure":963.0,"status":"TS","category":1,"agency":"nadi"},{"t":"2016-01-02T03:00:00Z","lat":-18.4,"lon":184.2,"wind":83.0,"pressure":961.0,"status":"TS","category":2,"agency":"nadi"},{"t":"2016-01-02T06:00:00Z","lat":-18.5,"lon":183.9,"wind":85.0,"pressure":959.0,"status":"TS","category":2,"agency":"nadi"},{"t":"2016-01-02T09:00:00Z","lat":-18.6,"lon":183.5,"wind":88.0,"pressure":958.0,"status":"TS","category":2,"agency":"nadi"},{"t":"2016-01-02T12:00:00Z","lat":-18.8,"lon":183.0,"wind":90.0,"pressure":956.0,"status":"TS","category":2,"agency":"nadi"},{"t":"2016-01-02T15:00:00Z","lat":-19.0,"lon":182.6,"wind":93.0,"pressure":954.0,"status":"TS","category":2,"agency":"nadi"},{"t":"2016-01-02T18:00:00Z","lat":-19.2,"lon":182.3,"wind":95.0,"pressure":952.0,"status":"TS","category":2,"agency":"nadi"},{"t":"2016-01-02T21:00:00Z","lat":-19.5,"lon":181.9,"wind":95.0,"pressure":952.0,"status":"TS","category":2,"agency":"nadi"},{"t":"2016-01-03T00:00:00Z","lat":-19.9,"lon":181.5,"wind":95.0,"pressure":952.0,"status":"TS","category":2,"agency":"nadi"},{"t":"2016-01-03T03:00:00Z","lat":-20.2,"lon":181.1,"wind":98.0,"pressure":950.0,"status":"TS","category":3,"agency":"nadi"},{"t":"2016-01-03T06:00:00Z","lat":-20.4,"lon":180.9,"wind":100.0,"pressure":948.0,"status":"TS","category":3,"agency":"nadi"},{"t":"2016-01-03T09:00:00Z","lat":-20.7,"lon":180.6,"wind":100.0,"pressure":948.0,"status":"TS","category":3,"agency":"nadi"},{"t":"2016-01-03T12:00:00Z","lat":-21.0,"lon":180.2,"wind":105.0,"pressure":944.0,"status":"TS","category":3,"agency":"nadi"},{"t":"2016-01-03T15:00:00Z","lat":-21.3,"lon":180.0,"wind":100.0,"pressure":948.0,"status":"TS","category":3,"agency":"nadi"},{"t":"2016-01-03T18:00:00Z","lat":-21.6,"lon":179.9,"wind":95.0,"pressure":952.0,"status":"TS","category":2,"agency":"nadi"},{"t":"2016-01-03T21:00:00Z","lat":-21.8,"lon":179.7,"wind":90.0,"pressure":956.0,"status":"TS","category":2,"agency":"nadi"},{"t":"2016-01-04T00:00:00Z","lat":-21.9,"lon":179.5,"wind":85.0,"pressure":959.0,"status":"TS","category":2,"agency":"nadi"},{"t":"2016-01-04T03:00:00Z","lat":-22.1,"lon":179.3,"wind":80.0,"pressure":963.0,"status":"TS","category":1,"agency":"nadi"},{"t":"2016-01-04T06:00:00Z","lat":-22.2,"lon":179.1,"wind":75.0,"pressure":967.0,"status":"TS","category":1,"agency":"nadi"},{"t":"2016-01-04T09:00:00Z","lat":-22.3,"lon":178.9,"wind":73.0,"pressure":969.0,"status":"TS","category":1,"agency":null},{"t":"2016-01-04T12:00:00Z","lat":-22.3,"lon":178.7,"wind":70.0,"pressure":970.0,"status":"TS","category":1,"agency":"nadi"},{"t":"2016-01-04T15:00:00Z","lat":-22.2,"lon":178.5,"wind":65.0,"pressure":974.0,"status":"TS","category":1,"agency":null},{"t":"2016-01-04T18:00:00Z","lat":-22.0,"lon":178.3,"wind":60.0,"pressure":978.0,"status":"TS","category":0,"agency":"nadi"},{"t":"2016-01-04T21:00:00Z","lat":-21.9,"lon":178.2,"wind":60.0,"pressure":978.0,"status":"TS","category":0,"agency":null},{"t":"2016-01-05T00:00:00Z","lat":-21.8,"lon":178.2,"wind":60.0,"pressure":978.0,"status":"TS","category":0,"agency":"nadi"},{"t":"2016-01-05T03:00:00Z","lat":-21.6,"lon":178.0,"wind":58.0,"pressure":980.0,"status":"TS","category":0,"agency":"nadi"},{"t":"2016-01-05T06:00:00Z","lat":-21.5,"lon":177.8,"wind":55.0,"pressure":982.0,"status":"TS","category":0,"agency":"nadi"},{"t":"2016-01-05T09:00:00Z","lat":-21.3,"lon":177.6,"wind":53.0,"pressure":984.0,"status":"TS","category":0,"agency":null},{"t":"2016-01-05T12:00:00Z","lat":-21.3,"lon":177.5,"wind":50.0,"pressure":985.0,"status":"TS","category":0,"agency":"nadi"},{"t":"2016-01-05T15:00:00Z","lat":-21.1,"lon":177.2,"wind":50.0,"pressure":985.0,"status":"TS","category":0,"agency":"nadi"},{"t":"2016-01-05T18:00:00Z","lat":-21.0,"lon":177.0,"wind":50.0,"pressure":985.0,"status":"TS","category":0,"agency":"nadi"},{"t":"2016-01-05T21:00:00Z","lat":-20.8,"lon":176.8,"wind":50.0,"pressure":985.0,"status":"TS","category":0,"agency":"nadi"},{"t":"2016-01-06T00:00:00Z","lat":-20.6,"lon":176.6,"wind":50.0,"pressure":985.0,"status":"TS","category":0,"agency":"nadi"},{"t":"2016-01-06T03:00:00Z","lat":-20.4,"lon":176.4,"wind":48.0,"pressure":987.0,"status":"TS","category":0,"agency":null},{"t":"2016-01-06T06:00:00Z","lat":-20.3,"lon":176.3,"wind":45.0,"pressure":989.0,"status":"TS","category":0,"agency":"nadi"},{"t":"2016-01-06T09:00:00Z","lat":-20.1,"lon":176.0,"wind":45.0,"pressure":989.0,"status":"TS","category":0,"agency":"nadi"},{"t":"2016-01-06T12:00:00Z","lat":-19.9,"lon":175.9,"wind":45.0,"pressure":989.0,"status":"TS","category":0,"agency":"nadi"},{"t":"2016-01-06T15:00:00Z","lat":-19.7,"lon":175.7,"wind":45.0,"pressure":989.0,"status":"TS","category":0,"agency":"nadi"},{"t":"2016-01-06T18:00:00Z","lat":-19.6,"lon":175.5,"wind":45.0,"pressure":989.0,"status":"TS","category":0,"agency":"nadi"},{"t":"2016-01-06T21:00:00Z","lat":-19.5,"lon":175.3,"wind":45.0,"pressure":989.0,"status":"TS","category":0,"agency":null},{"t":"2016-01-07T00:00:00Z","lat":-19.5,"lon":175.3,"wind":45.0,"pressure":989.0,"status":"TS","category":0,"agency":null},{"t":"2016-01-07T03:00:00Z","lat":-19.4,"lon":175.2,"wind":48.0,"pressure":987.0,"status":"TS","category":0,"agency":null},{"t":"2016-01-07T06:00:00Z","lat":-19.3,"lon":175.1,"wind":50.0,"pressure":985.0,"status":"TS","category":0,"agency":"nadi"},{"t":"2016-01-07T09:00:00Z","lat":-19.1,"lon":174.9,"wind":53.0,"pressure":984.0,"status":"TS","category":0,"agency":"nadi"},{"t":"2016-01-07T12:00:00Z","lat":-18.9,"lon":174.8,"wind":55.0,"pressure":982.0,"status":"TS","category":0,"agency":"nadi"},{"t":"2016-01-07T15:00:00Z","lat":-18.8,"lon":174.6,"wind":55.0,"pressure":982.0,"status":"TS","category":0,"agency":null},{"t":"2016-01-07T18:00:00Z","lat":-18.7,"lon":174.6,"wind":55.0,"pressure":982.0,"status":"TS","category":0,"agency":"nadi"},{"t":"2016-01-07T21:00:00Z","lat":-18.6,"lon":174.5,"wind":55.0,"pressure":982.0,"status":"TS","category":0,"agency":"nadi"},{"t":"2016-01-08T00:00:00Z","lat":-18.5,"lon":174.4,"wind":55.0,"pressure":982.0,"status":"TS","category":0,"agency":"nadi"},{"t":"2016-01-08T03:00:00Z","lat":-18.4,"lon":174.2,"wind":58.0,"pressure":980.0,"status":"TS","category":0,"agency":null},{"t":"2016-01-08T06:00:00Z","lat":-18.4,"lon":174.2,"wind":60.0,"pressure":978.0,"status":"TS","category":0,"agency":"nadi"},{"t":"2016-01-08T09:00:00Z","lat":-18.4,"lon":174.1,"wind":65.0,"pressure":974.0,"status":"TS","category":1,"agency":null},{"t":"2016-01-08T12:00:00Z","lat":-18.4,"lon":174.0,"wind":70.0,"pressure":970.0,"status":"TS","category":1,"agency":"nadi"},{"t":"2016-01-08T15:00:00Z","lat":-18.4,"lon":173.8,"wind":75.0,"pressure":967.0,"status":"TS","category":1,"agency":null},{"t":"2016-01-08T18:00:00Z","lat":-18.4,"lon":173.7,"wind":80.0,"pressure":963.0,"status":"TS","category":1,"agency":"nadi"},{"t":"2016-01-08T21:00:00Z","lat":-18.4,"lon":173.5,"wind":83.0,"pressure":961.0,"status":"TS","category":2,"agency":null},{"t":"2016-01-09T00:00:00Z","lat":-18.6,"lon":173.4,"wind":85.0,"pressure":959.0,"status":"TS","category":2,"agency":"nadi"},{"t":"2016-01-09T03:00:00Z","lat":-18.7,"lon":173.2,"wind":88.0,"pressure":958.0,"status":"TS","category":2,"agency":"nadi"},{"t":"2016-01-09T06:00:00Z","lat":-18.8,"lon":173.0,"wind":90.0,"pressure":956.0,"status":"TS","category":2,"agency":"nadi"},{"t":"2016-01-09T09:00:00Z","lat":-18.9,"lon":172.7,"wind":95.0,"pressure":952.0,"status":"TS","category":2,"agency":"nadi"},{"t":"2016-01-09T12:00:00Z","lat":-19.1,"lon":172.4,"wind":100.0,"pressure":948.0,"status":"TS","category":3,"agency":"nadi"},{"t":"2016-01-09T15:00:00Z","lat":-19.2,"lon":172.0,"wind":105.0,"pressure":945.0,"status":"TS","category":3,"agency":"nadi"},{"t":"2016-01-09T18:00:00Z","lat":-19.3,"lon":171.9,"wind":110.0,"pressure":941.0,"status":"TS","category":3,"agency":"nadi"},{"t":"2016-01-09T21:00:00Z","lat":-19.6,"lon":171.5,"wind":115.0,"pressure":937.0,"status":"TS","category":4,"agency":"nadi"},{"t":"2016-01-10T00:00:00Z","lat":-19.9,"lon":171.3,"wind":120.0,"pressure":933.0,"status":"TS","category":4,"agency":"nadi"},{"t":"2016-01-10T03:00:00Z","lat":-20.1,"lon":171.0,"wind":118.0,"pressure":935.0,"status":"TS","category":4,"agency":"nadi"},{"t":"2016-01-10T05:00:00Z","lat":-20.3,"lon":170.7,"wind":116.0,"pressure":936.0,"status":"TS","category":4,"agency":"nadi"},{"t":"2016-01-10T06:00:00Z","lat":-20.4,"lon":170.7,"wind":115.0,"pressure":937.0,"status":"TS","category":4,"agency":null},{"t":"2016-01-10T07:00:00Z","lat":-20.5,"lon":170.6,"wind":114.0,"pressure":938.0,"status":"TS","category":4,"agency":"nadi"},{"t":"2016-01-10T09:00:00Z","lat":-20.8,"lon":170.4,"wind":113.0,"pressure":939.0,"status":"TS","category":4,"agency":"nadi"},{"t":"2016-01-10T11:00:00Z","lat":-21.0,"lon":170.3,"wind":111.0,"pressure":940.0,"status":"TS","category":3,"agency":"nadi"},{"t":"2016-01-10T12:00:00Z","lat":-21.2,"lon":170.2,"wind":110.0,"pressure":941.0,"status":"TS","category":3,"agency":null},{"t":"2016-01-10T15:00:00Z","lat":-21.5,"lon":170.1,"wind":108.0,"pressure":943.0,"status":"TS","category":3,"agency":"nadi"},{"t":"2016-01-10T18:00:00Z","lat":-21.9,"lon":170.1,"wind":105.0,"pressure":944.0,"status":"TS","category":3,"agency":"nadi"},{"t":"2016-01-10T21:00:00Z","lat":-22.4,"lon":169.9,"wind":100.0,"pressure":948.0,"status":"TS","category":3,"agency":"nadi"},{"t":"2016-01-11T00:00:00Z","lat":-22.9,"lon":169.9,"wind":95.0,"pressure":952.0,"status":"TS","category":2,"agency":"nadi"},{"t":"2016-01-11T03:00:00Z","lat":-23.6,"lon":169.9,"wind":93.0,"pressure":954.0,"status":"TS","category":2,"agency":"nadi"},{"t":"2016-01-11T06:00:00Z","lat":-24.1,"lon":170.0,"wind":90.0,"pressure":956.0,"status":"TS","category":2,"agency":"nadi"},{"t":"2016-01-11T09:00:00Z","lat":-24.7,"lon":170.2,"wind":83.0,"pressure":962.0,"status":"TS","category":2,"agency":"nadi"},{"t":"2016-01-11T12:00:00Z","lat":-25.1,"lon":170.4,"wind":75.0,"pressure":967.0,"status":"TS","category":1,"agency":"wellington"},{"t":"2016-01-11T15:00:00Z","lat":-25.6,"lon":170.6,"wind":70.0,"pressure":971.0,"status":"TS","category":1,"agency":null},{"t":"2016-01-11T18:00:00Z","lat":-26.1,"lon":170.9,"wind":65.0,"pressure":974.0,"status":"TS","category":1,"agency":"wellington"},{"t":"2016-01-11T21:00:00Z","lat":-26.6,"lon":171.2,"wind":60.0,"pressure":978.0,"status":"TS","category":0,"agency":null},{"t":"2016-01-12T00:00:00Z","lat":-27.1,"lon":171.7,"wind":55.0,"pressure":982.0,"status":"TS","category":0,"agency":"wellington"},{"t":"2016-01-12T03:00:00Z","lat":-27.8,"lon":172.2,"wind":53.0,"pressure":984.0,"status":"TS","category":0,"agency":null},{"t":"2016-01-12T06:00:00Z","lat":-28.3,"lon":172.9,"wind":50.0,"pressure":985.0,"status":"TS","category":0,"agency":"wellington"},{"t":"2016-01-12T09:00:00Z","lat":-28.7,"lon":173.5,"wind":48.0,"pressure":987.0,"status":"TS","category":0,"agency":null},{"t":"2016-01-12T12:00:00Z","lat":-29.0,"lon":174.1,"wind":45.0,"pressure":989.0,"status":"TS","category":0,"agency":"wellington"},{"t":"2016-01-12T15:00:00Z","lat":-29.2,"lon":174.5,"wind":40.0,"pressure":993.0,"status":"TS","category":0,"agency":null},{"t":"2016-01-12T18:00:00Z","lat":-29.5,"lon":175.0,"wind":35.0,"pressure":996.0,"status":"TS","category":0,"agency":"wellington"},{"t":"2016-01-12T21:00:00Z","lat":-29.8,"lon":175.6,"wind":33.0,"pressure":998.0,"status":"TS","category":-1,"agency":null},{"t":"2016-01-13T00:00:00Z","lat":-30.0,"lon":176.2,"wind":30.0,"pressure":1000.0,"status":"SS","category":-1,"agency":"wellington"},{"t":"2016-01-13T03:00:00Z","lat":-30.2,"lon":176.8,"wind":30.0,"pressure":1000.0,"status":"SS","category":-1,"agency":null},{"t":"2016-01-13T06:00:00Z","lat":-30.2,"lon":177.4,"wind":30.0,"pressure":1000.0,"status":"SS","category":-1,"agency":"wellington"},{"t":"2016-01-13T09:00:00Z","lat":-30.3,"lon":177.8,"wind":null,"pressure":null,"status":"NR","category":null,"agency":null},{"t":"2016-01-13T12:00:00Z","lat":-30.3,"lon":178.0,"wind":30.0,"pressure":1005.0,"status":"NR","category":-1,"agency":"wellington"},{"t":"2016-01-13T15:00:00Z","lat":-30.3,"lon":178.3,"wind":null,"pressure":null,"status":"NR","category":null,"agency":null},{"t":"2016-01-13T18:00:00Z","lat":-30.2,"lon":178.6,"wind":30.0,"pressure":1006.0,"status":"NR","category":-1,"agency":"wellington"},{"t":"2016-01-13T21:00:00Z","lat":-29.9,"lon":179.0,"wind":null,"pressure":null,"status":"NR","category":null,"agency":null},{"t":"2016-01-14T00:00:00Z","lat":-29.5,"lon":179.3,"wind":30.0,"pressure":1006.0,"status":"NR","category":-1,"agency":"wellington"},{"t":"2016-01-14T03:00:00Z","lat":-29.1,"lon":179.6,"wind":null,"pressure":null,"status":"NR","category":null,"agency":null},{"t":"2016-01-14T06:00:00Z","lat":-28.8,"lon":179.7,"wind":30.0,"pressure":1006.0,"status":"NR","category":-1,"agency":"wellington"},{"t":"2016-01-14T09:00:00Z","lat":-28.6,"lon":179.7,"wind":null,"pressure":null,"status":"NR","category":null,"agency":null},{"t":"2016-01-14T12:00:00Z","lat":-28.5,"lon":179.4,"wind":30.0,"pressure":1007.0,"status":"NR","category":-1,"agency":"wellington"},{"t":"2016-01-14T15:00:00Z","lat":-28.8,"lon":178.8,"wind":null,"pressure":null,"status":"NR","category":null,"agency":null},{"t":"2016-01-14T18:00:00Z","lat":-29.1,"lon":178.1,"wind":25.0,"pressure":1007.0,"status":"NR","category":-1,"agency":"wellington"},{"t":"2016-01-14T21:00:00Z","lat":-28.9,"lon":177.3,"wind":null,"pressure":null,"status":"NR","category":null,"agency":null},{"t":"2016-01-15T00:00:00Z","lat":-28.6,"lon":176.5,"wind":25.0,"pressure":1007.0,"status":"NR","category":-1,"agency":"wellington"},{"t":"2016-01-15T03:00:00Z","lat":-28.3,"lon":176.1,"wind":null,"pressure":null,"status":"NR","category":null,"agency":null},{"t":"2016-01-15T06:00:00Z","lat":-28.2,"lon":175.7,"wind":25.0,"pressure":1007.0,"status":"NR","category":-1,"agency":"wellington"},{"t":"2016-01-15T09:00:00Z","lat":-28.4,"lon":175.2,"wind":null,"pressure":null,"status":"NR","category":null,"agency":null},{"t":"2016-01-15T12:00:00Z","lat":-28.6,"lon":174.6,"wind":20.0,"pressure":1009.0,"status":"NR","category":-1,"agency":"wellington"},{"t":"2016-01-15T15:00:00Z","lat":-28.6,"lon":174.0,"wind":null,"pressure":null,"status":"NR","category":null,"agency":null},{"t":"2016-01-15T18:00:00Z","lat":-28.5,"lon":173.4,"wind":20.0,"pressure":1009.0,"status":"NR","category":-1,"agency":"wellington"},{"t":"2016-01-15T21:00:00Z","lat":-28.4,"lon":172.9,"wind":null,"pressure":null,"status":"NR","category":null,"agency":null},{"t":"2016-01-16T00:00:00Z","lat":-28.4,"lon":172.4,"wind":20.0,"pressure":1009.0,"status":"NR","category":-1,"agency":"wellington"},{"t":"2016-01-16T03:00:00Z","lat":-28.4,"lon":172.1,"wind":null,"pressure":null,"status":"NR","category":null,"agency":null},{"t":"2016-01-16T06:00:00Z","lat":-28.4,"lon":171.8,"wind":20.0,"pressure":1009.0,"status":"NR","category":-1,"agency":"wellington"}]